FastSQLModel/__init__.py
FastSQLModel/_modidx.py
FastSQLModel/cli.py
FastSQLModel/db.py
FastSQLModel/templates/README
FastSQLModel/templates/__init__.py
FastSQLModel/templates/alembic.ini.mako
FastSQLModel/templates/env.py
FastSQLModel/templates/script.py.mako
FastSQLModel-0.1.6.dist-info/LICENSE
FastSQLModel-0.1.6.dist-info/METADATA
FastSQLModel-0.1.6.dist-info/WHEEL
FastSQLModel-0.1.6.dist-info/entry_points.txt
FastSQLModel-0.1.6.dist-info/top_level.txt
FastSQLModel-0.1.6.dist-info/RECORD
