Metadata-Version: 2.1
Name: FastSQLModel
Version: 0.1.6
Summary: Simplie and Fast utility for SQLModel/SQLAlchemy and Alembic
Home-page: https://github.com/ndendic/FastSQLModel
Author: Nikola Dendic
Author-email: Nikola Dendic <ndendic@gmail.com>
License: Apache Software License 2.0
Keywords: nbdev jupyter notebook python
Classifier: Development Status :: 4 - Beta
Classifier: Intended Audience :: Developers
Classifier: Natural Language :: English
Classifier: Programming Language :: Python :: 3.7
Classifier: Programming Language :: Python :: 3.8
Classifier: Programming Language :: Python :: 3.9
Classifier: Programming Language :: Python :: 3.10
Classifier: Programming Language :: Python :: 3.11
Classifier: Programming Language :: Python :: 3.12
Classifier: License :: OSI Approved :: Apache Software License
Requires-Python: >=3.7
License-File: LICENSE
Requires-Dist: alembic>=1.14.0
Requires-Dist: setuptools>=75.6.0
Requires-Dist: sqlmodel>=0.0.22
Requires-Dist: typer[all]>=0.15.1
Provides-Extra: dev
